pandas_plots/_DEPR/hlp.py
pandas_plots/_DEPR/pls.py
pandas_plots/_DEPR/tbl.py
pandas_plots/_DEPR/ven.py
pandas_plots/__init__.py
pandas_plots/cli/__init__.py
pandas_plots/cli/converter.py
pandas_plots/helper.py
pandas_plots/hlp/__init__.py
pandas_plots/hlp/add_bitmask_label.py
pandas_plots/hlp/add_datetime_columns.py
pandas_plots/hlp/add_measures_to_pyg_config.py
pandas_plots/hlp/create_barcode_from_url.py
pandas_plots/hlp/create_py_script.py
pandas_plots/hlp/find_cols.py
pandas_plots/hlp/get_duckdb_filter_n.py
pandas_plots/hlp/get_sparse_df.py
pandas_plots/hlp/get_tum_details.py
pandas_plots/hlp/group_kkr.py
pandas_plots/hlp/is_ipynb.py
pandas_plots/hlp/mean_confidence_interval.py
pandas_plots/hlp/prepend_uv_header.py
pandas_plots/hlp/print_filter.py
pandas_plots/hlp/replace_delimiter_outside_quotes.py
pandas_plots/hlp/set_theme.py
pandas_plots/hlp/show_package_version_get_os.py
pandas_plots/hlp/to_series.py
pandas_plots/hlp/wrap_text.py
pandas_plots/pls/__init__.py
pandas_plots/pls/plot_bars.py
pandas_plots/pls/plot_box.py
pandas_plots/pls/plot_box_large.py
pandas_plots/pls/plot_boxes.py
pandas_plots/pls/plot_boxes_large.py
pandas_plots/pls/plot_facet_stacked_bars.py
pandas_plots/pls/plot_histogram.py
pandas_plots/pls/plot_histogram_large.py
pandas_plots/pls/plot_joint.py
pandas_plots/pls/plot_pie.py
pandas_plots/pls/plot_quadrants.py
pandas_plots/pls/plot_sankey.py
pandas_plots/pls/plot_stacked_bars.py
pandas_plots/pls/plot_uml_graph.py
pandas_plots/pls/plot_upset.py
pandas_plots/tbl/__init__.py
pandas_plots/tbl/descr_db.py
pandas_plots/tbl/describe_df.py
pandas_plots/tbl/pivot_df.py
pandas_plots/tbl/print_summary.py
pandas_plots/tbl/show_num_df.py
pandas_plots/ven/__init__.py
pandas_plots/ven/show_venn2.py
pandas_plots/ven/show_venn3.py
pandas_plots-1.2.2.dist-info/WHEEL
pandas_plots-1.2.2.dist-info/entry_points.txt
pandas_plots-1.2.2.dist-info/METADATA
pandas_plots-1.2.2.dist-info/RECORD
