Metadata-Version: 2.3
Name: pandas-plots
Version: 1.2.2
Summary: A collection of helper for table handling and visualization
Keywords: tables,pivot,plotly,venn,plot,vizualization
Author: smeisegeier
Author-email: smeisegeier <dexterDSD@googlemail.com>
Classifier: License :: OSI Approved :: MIT License
Classifier: Programming Language :: Python :: 3
Classifier: Programming Language :: Python :: 3.12
Classifier: Development Status :: 5 - Production/Stable
Classifier: Intended Audience :: Science/Research
Classifier: Operating System :: OS Independent
Classifier: Topic :: Scientific/Engineering
Requires-Dist: pandas>=2.3.2
Requires-Dist: plotly>=6.2
Requires-Dist: kaleido>=1
Requires-Dist: matplotlib>=3.10.0
Requires-Dist: matplotlib-inline
Requires-Dist: matplotlib-venn==0.11.10
Requires-Dist: seaborn>=0.13.2
Requires-Dist: jinja2>=3.1.4
Requires-Dist: requests>=2.32.0
Requires-Dist: numpy<2.0.0
Requires-Dist: missingno>=0.5.2
Requires-Dist: duckdb>=1.3.0
Requires-Dist: nbformat>=4.2.0
Requires-Dist: dataframe-image>=0.2.7
Requires-Dist: connection-helper>=0.13.1
Requires-Dist: upsetplot>=0.9.0
Requires-Dist: ipynbname>=2025.8.0.0
Requires-Python: >=3.11
Project-URL: Bug Tracker, https://github.com/smeisegeier/pandas-plots/issues
Project-URL: Homepage, https://github.com/smeisegeier/pandas-plots
Project-URL: Repository, https://github.com/smeisegeier/pandas-plots
